dipswitch/__init__.py
dipswitch-1.0.dist-info/METADATA
dipswitch-1.0.dist-info/RECORD
dipswitch-1.0.dist-info/WHEEL
dipswitch-1.0.dist-info/top_level.txt
