Metadata-Version: 2.1
Name: dipswitch
Version: 1.0
Summary: Switch statements for Python
Home-page: https://home.exetel.com.au/declanhoare/projects/dipswitch.git
Author: Declan Hoare
Author-email: declanhoare@exemail.com.au
License: UNKNOWN
Platform: UNKNOWN
Classifier: Programming Language :: Python :: 3
Classifier: License :: OSI Approved :: GNU General Public License v3 or later (GPLv3+)
Classifier: Operating System :: OS Independent
